Metadata-Version: 2.4
Name: mcp_client_cli
Version: 1.0.4
Summary: Command line interface for MCP client
Project-URL: Homepage, https://github.com/adhikasp/mcp_client_cli
Project-URL: Issues, https://github.com/adhikasp/mcp_client_cli/issues
Author-email: Adhika Setya Pramudita <adhika.setya.p@gmail.com>
License: MIT
License-File: LICENSE
Classifier: License :: OSI Approved :: MIT License
Classifier: Operating System :: OS Independent
Classifier: Programming Language :: Python :: 3
Requires-Python: >=3.12
Requires-Dist: aiosqlite>=0.20.0
Requires-Dist: commentjson>=0.9.0
Requires-Dist: jsonschema-pydantic>=0.6
Requires-Dist: langchain-anthropic>=0.3.0
Requires-Dist: langchain-google-genai>=2.0.7
Requires-Dist: langchain-openai>=0.2.10
Requires-Dist: langchain>=0.3.8
Requires-Dist: langgraph-checkpoint-sqlite>=2.0.1
Requires-Dist: langgraph-prebuilt>=0.1.0
Requires-Dist: langgraph>=0.4.1
Requires-Dist: mcp>=1.6.0
Requires-Dist: python-dotenv>=1.0.1
Requires-Dist: pywin32>=306; sys_platform == 'win32' or platform_system == 'Windows'
Requires-Dist: rich>=13.9.0
Requires-Dist: standard-imghdr>=3.13.0
Provides-Extra: clipboard
Requires-Dist: pngpaste; (sys_platform == 'darwin' and python_version < '3.12') and extra == 'clipboard'
Requires-Dist: pyperclip>=1.8.2; extra == 'clipboard'
